{
    "type": "FeatureCollection", 
    "features": [
        {
            "type": "Feature", 
            "properties": {
                "name": "Equatorial_Pacific_E175.0_N00.0", 
                "tags": "seed_point", 
                "object": "point", 
                "component": "ocean", 
                "author": "Todd Ringler"
            }, 
            "geometry": {
                "type": "Point", 
                "coordinates": [
                    175.000000, 
                    0.000000
                ]
            }
        }
    ]
}